[
  {
    "tango": "建前",
    "yomikata": "たてまえ",
    "imi": "(표면상의) 방침, 원칙"
  },
  {
    "tango": "封じる",
    "yomikata": "ふうじる",
    "imi": "밀봉하다, 봉쇄하다"
  },
  {
    "tango": "感染",
    "yomikata": "かんせん",
    "imi": "감염"
  },
  {
    "tango": "処置",
    "yomikata": "しょち",
    "imi": "처치, 조치"
  },
  {
    "tango": "改革",
    "yomikata": "かいかく",
    "imi": "개혁"
  },
  {
    "tango": "推理",
    "yomikata": "すいり",
    "imi": "추리"
  },
  {
    "tango": "カテゴリー",
    "yomikata": "",
    "imi": "카테고리, 범주"
  },
  {
    "tango": "合法",
    "yomikata": "ごうほう",
    "imi": "합법"
  },
  {
    "tango": "同然",
    "yomikata": "どうぜん",
    "imi": "똑같음, 다름없음"
  },
  {
    "tango": "直面",
    "yomikata": "ちょくめん",
    "imi": "직면"
  },
  {
    "tango": "古代",
    "yomikata": "こだい",
    "imi": "고대"
  },
  {
    "tango": "きっちり",
    "yomikata": "",
    "imi": "① 빈틈없이, 꽉=ぴったり ② 딱, 정확하게 = きっかり"
  },
  {
    "tango": "なにとぞ",
    "yomikata": "",
    "imi": "부디, 아무쪼록 = どうぞ, どうか"
  },
  {
    "tango": "募る",
    "yomikata": "つのる",
    "imi": "모집하다, 점점 심해지다"
  },
  {
    "tango": "精鋭",
    "yomikata": "せいえい",
    "imi": "정예, 선택된 소수의 인재"
  },
  {
    "tango": "手引き",
    "yomikata": "てびき",
    "imi": "안내, 안내인"
  },
  {
    "tango": "耐えがたい",
    "yomikata": "たえがたい",
    "imi": "견디기 어렵다"
  },
  {
    "tango": "ストライキ",
    "yomikata": "",
    "imi": "스트라이크, 파업"
  },
  {
    "tango": "承諾",
    "yomikata": "しょうだく",
    "imi": "승낙"
  },
  {
    "tango": "親善",
    "yomikata": "しんぜん",
    "imi": "친선, 사이가 좋게 함"
  },
  {
    "tango": "乗り出す",
    "yomikata": "のりだす",
    "imi": "적극적으로 나서다"
  },
  {
    "tango": "新型",
    "yomikata": "しんがた",
    "imi": "신형"
  },
  {
    "tango": "発端",
    "yomikata": "ほったん",
    "imi": "발단"
  },
  {
    "tango": "かぶれる",
    "yomikata": "",
    "imi": "염증을 일으키다, 푹 빠지다"
  },
  {
    "tango": "優美な",
    "yomikata": "ゆうびな",
    "imi": "우아한"
  },
  {
    "tango": "究極",
    "yomikata": "きゅうきょく",
    "imi": "궁극"
  },
  {
    "tango": "切実な",
    "yomikata": "せつじつな",
    "imi": "절실한"
  },
  {
    "tango": "細胞",
    "yomikata": "さいぼう",
    "imi": "세포"
  },
  {
    "tango": "申し出る",
    "yomikata": "もうしでる",
    "imi": "(의견, 희망을) 신청하다. 제의하다"
  },
  {
    "tango": "担う",
    "yomikata": "になう",
    "imi": "짊어지다, 떠맡다"
  },
  {
    "tango": "揉める",
    "yomikata": "もめる",
    "imi": "옥신각신하다"
  },
  {
    "tango": "襲擊",
    "yomikata": "しゅうげき",
    "imi": "습격"
  },
  {
    "tango": "出没",
    "yomikata": "しゅつぼつ",
    "imi": "출몰"
  },
  {
    "tango": "なるたけ",
    "yomikata": "",
    "imi": "되도록, 가능한 한=できるだけ, なるべく"
  },
  {
    "tango": "腫れる",
    "yomikata": "はれる",
    "imi": "붓다, 부어오르다"
  },
  {
    "tango": "支障",
    "yomikata": "ししょう",
    "imi": "지장"
  },
  {
    "tango": "否定的な",
    "yomikata": "ひていてきな",
    "imi": "부정적인"
  },
  {
    "tango": "値打ち",
    "yomikata": "ねうち",
    "imi": "값어치, 가치, 가격"
  },
  {
    "tango": "無駄な",
    "yomikata": "むだな",
    "imi": "쓸데없는, 헛된"
  },
  {
    "tango": "修行",
    "yomikata": "しゅぎょう",
    "imi": "수행"
  },
  {
    "tango": "爆弾",
    "yomikata": "ばくだん",
    "imi": "폭탄"
  },
  {
    "tango": "返済",
    "yomikata": "へんさい",
    "imi": "상환, 갚음"
  },
  {
    "tango": "謝罪",
    "yomikata": "しゃざい",
    "imi": "사죄"
  },
  {
    "tango": "推測",
    "yomikata": "すいそく",
    "imi": "추측"
  },
  {
    "tango": "反感",
    "yomikata": "はんかん",
    "imi": "반감"
  },
  {
    "tango": "悲願",
    "yomikata": "ひがん",
    "imi": "비원, 비장한 소원"
  }
]