[
  {
    "tango": "鉄橋",
    "yomikata": "てっきょう",
    "imi": "철교"
  },
  {
    "tango": "救助",
    "yomikata": "きゅうじょ",
    "imi": "구조"
  },
  {
    "tango": "焼き物",
    "yomikata": "やきもの",
    "imi": "① 도자기   ② 구이 요리"
  },
  {
    "tango": "再び",
    "yomikata": "ふたたび",
    "imi": "다시"
  },
  {
    "tango": "地点",
    "yomikata": "ちてん",
    "imi": "지점"
  },
  {
    "tango": "極端な",
    "yomikata": "きょくたんな",
    "imi": "극단적인"
  },
  {
    "tango": "質",
    "yomikata": "しつ",
    "imi": "질, 품질"
  },
  {
    "tango": "生意気な",
    "yomikata": "なまいきな",
    "imi": "건방진, 주제 넘은"
  },
  {
    "tango": "吸収",
    "yomikata": "きゅうしゅう",
    "imi": "흡수"
  },
  {
    "tango": "ぶら下げる",
    "yomikata": "ぶらさげる",
    "imi": "늘어뜨리다, 매달다, (손에) 들다"
  },
  {
    "tango": "看病",
    "yomikata": "かんびょう",
    "imi": "간병"
  },
  {
    "tango": "きっかけ",
    "yomikata": "",
    "imi": "계기"
  },
  {
    "tango": "損",
    "yomikata": "そん",
    "imi": "손해, 손실"
  },
  {
    "tango": "つまずく",
    "yomikata": "",
    "imi": "발이 걸려 넘어지다, 좌절하다"
  },
  {
    "tango": "想定",
    "yomikata": "そうてい",
    "imi": "상정, 가정, 전제"
  },
  {
    "tango": "くれぐれも",
    "yomikata": "",
    "imi": "부디, 아무쪼록"
  },
  {
    "tango": "神経",
    "yomikata": "しんけい",
    "imi": "신경"
  },
  {
    "tango": "前期",
    "yomikata": "ぜんき",
    "imi": "전기"
  },
  {
    "tango": "規律",
    "yomikata": "きりつ",
    "imi": "규율"
  },
  {
    "tango": "候補",
    "yomikata": "こうほ",
    "imi": "후보"
  },
  {
    "tango": "城",
    "yomikata": "しろ",
    "imi": "성, 성곽"
  },
  {
    "tango": "かじる",
    "yomikata": "",
    "imi": "갉아먹다"
  },
  {
    "tango": "平野",
    "yomikata": "へいや",
    "imi": "평야, 들"
  },
  {
    "tango": "南米",
    "yomikata": "なんべい",
    "imi": "남미"
  },
  {
    "tango": "ひっくり返る",
    "yomikata": "ひっくりかえる",
    "imi": "뒤집히다, 엎어지다"
  },
  {
    "tango": "蛍光灯",
    "yomikata": "けいこうとう",
    "imi": "형광등"
  },
  {
    "tango": "荒れる",
    "yomikata": "あれる",
    "imi": "거칠어지다"
  },
  {
    "tango": "休まる",
    "yomikata": "やすまる",
    "imi": "편안해지다, 피로가 풀리다"
  },
  {
    "tango": "考慮",
    "yomikata": "こうりょ",
    "imi": "고려"
  },
  {
    "tango": "着々と",
    "yomikata": "ちゃくちゃくと",
    "imi": "척척, 순조롭게"
  },
  {
    "tango": "講師",
    "yomikata": "こうし",
    "imi": "강사"
  },
  {
    "tango": "のろい",
    "yomikata": "",
    "imi": "느리다, 둔하다"
  },
  {
    "tango": "一人暮らし",
    "yomikata": "ひとりぐらし",
    "imi": "혼자서 삶, 독신 생활"
  },
  {
    "tango": "保証",
    "yomikata": "ほしょう",
    "imi": "보증"
  },
  {
    "tango": "~順 (접미어)",
    "yomikata": "~じゅん",
    "imi": "~순(순서)"
  },
  {
    "tango": "立場",
    "yomikata": "たちば",
    "imi": "입장"
  },
  {
    "tango": "敷く",
    "yomikata": "しく",
    "imi": "깔다"
  },
  {
    "tango": "少子化",
    "yomikata": "しょうしか",
    "imi": "출산율 저하"
  },
  {
    "tango": "象徴",
    "yomikata": "しょうちょう",
    "imi": "상징"
  },
  {
    "tango": "墓",
    "yomikata": "はか",
    "imi": "무덤"
  },
  {
    "tango": "暴行",
    "yomikata": "ぼうこう",
    "imi": "폭행"
  },
  {
    "tango": "尻尾",
    "yomikata": "しっぽ",
    "imi": "꼬리"
  },
  {
    "tango": "荒い",
    "yomikata": "あらい",
    "imi": "거칠다, 거세다"
  },
  {
    "tango": "金庫",
    "yomikata": "きんこ",
    "imi": "금고"
  },
  {
    "tango": "武士",
    "yomikata": "ぶし",
    "imi": "무사"
  }
]